examples/django/helloworld/manage.py
examples/django/helloworld/helloworld/__init__.py
examples/django/helloworld/helloworld/asgi.py
examples/django/helloworld/helloworld/pbesa.py
examples/django/helloworld/helloworld/settings.py
examples/django/helloworld/helloworld/urls.py
examples/django/helloworld/helloworld/wsgi.py
examples/django/helloworld/translate/__init__.py
examples/django/helloworld/translate/admin.py
examples/django/helloworld/translate/apps.py
examples/django/helloworld/translate/models.py
examples/django/helloworld/translate/tests.py
examples/django/helloworld/translate/urls.py
examples/django/helloworld/translate/views.py
examples/django/helloworld/translate/mas/controller/translatecontroller.py
examples/django/helloworld/translate/mas/controller/translatedelegate.py
examples/django/helloworld/translate/mas/controller/translateresponse.py
examples/django/helloworld/translate/mas/worker/translatetask.py
examples/django/helloworld/translate/mas/worker/workeragent.py
examples/django/helloworld/translate/migrations/__init__.py
examples/remote/remote_a.py
examples/remote/remote_b.py
examples/remote/remote_c.py
examples/remote/mas/controller/countercontroller.py
examples/remote/mas/controller/counterdelegate.py
examples/remote/mas/controller/counterresponse.py
examples/remote/mas/worker/counteragent.py
examples/remote/mas/worker/countertask.py
examples/scripts/get_start.py
examples/scripts/remote_agent.py
examples/scripts/cognitive/augmented_generation.py
examples/scripts/cognitive/production.py
examples/scripts/cognitive/use_model.py
examples/scripts/social/collaborative_team.py
examples/scripts/social/delegator_team.py
examples/scripts/social/dispatcher_team.py
examples/scripts/social/free_team.py
examples/scripts/social/pipeline_team.py
examples/scripts/social/secuential_team.py
examples/scripts/social/simple_delegator_team.py
examples/scripts/social/simple_dispatcher_team.py
pbesa/__init__.py
pbesa/ai_client.py
pbesa/cognitive.py
pbesa/mas.py
pbesa-4.0.64.dist-info/licenses/LICENSE
pbesa-4.0.64.dist-info/METADATA
pbesa-4.0.64.dist-info/WHEEL
pbesa-4.0.64.dist-info/top_level.txt
pbesa-4.0.64.dist-info/RECORD
