Metadata-Version: 2.4
Name: pbesa
Version: 4.0.64
Summary: Plataforma para crear sistemas multiagentes racionales
Author: PBESA Team
License-Expression: MIT
Classifier: Development Status :: 4 - Beta
Classifier: Intended Audience :: Developers
Classifier: Programming Language :: Python :: 3
Classifier: Programming Language :: Python :: 3.8
Classifier: Programming Language :: Python :: 3.9
Classifier: Programming Language :: Python :: 3.10
Classifier: Programming Language :: Python :: 3.11
Classifier: Programming Language :: Python :: 3.12
Requires-Python: >=3.8
License-File: LICENSE
Requires-Dist: pymongo>=4.6.3
Requires-Dist: requests>=2.32.3
Requires-Dist: azure-ai-projects>=1.0.0b6
Requires-Dist: azure-ai-inference>=1.0.0b9
Requires-Dist: azure-identity>=1.21.0
Requires-Dist: pandas>=2.2.3
Requires-Dist: scikit-learn>=1.6.1
Requires-Dist: fuzzywuzzy>=0.18.0
Dynamic: license-file
